xrpl_dex_sdk/__init__.py
xrpl_dex_sdk/clients.py
xrpl_dex_sdk/constants.py
xrpl_dex_sdk/data/__init__.py
xrpl_dex_sdk/data/currencies.json
xrpl_dex_sdk/data/issuers.json
xrpl_dex_sdk/data/markets.json
xrpl_dex_sdk/methods/__init__.py
xrpl_dex_sdk/methods/cancel_order.py
xrpl_dex_sdk/methods/create_limit_buy_order.py
xrpl_dex_sdk/methods/create_limit_sell_order.py
xrpl_dex_sdk/methods/create_order.py
xrpl_dex_sdk/methods/create_trust_line.py
xrpl_dex_sdk/methods/fetch_balance.py
xrpl_dex_sdk/methods/fetch_canceled_orders.py
xrpl_dex_sdk/methods/fetch_closed_orders.py
xrpl_dex_sdk/methods/fetch_currencies.py
xrpl_dex_sdk/methods/fetch_fees.py
xrpl_dex_sdk/methods/fetch_issuers.py
xrpl_dex_sdk/methods/fetch_l2_order_book.py
xrpl_dex_sdk/methods/fetch_market.py
xrpl_dex_sdk/methods/fetch_markets.py
xrpl_dex_sdk/methods/fetch_my_trades.py
xrpl_dex_sdk/methods/fetch_open_orders.py
xrpl_dex_sdk/methods/fetch_order.py
xrpl_dex_sdk/methods/fetch_order_book.py
xrpl_dex_sdk/methods/fetch_order_books.py
xrpl_dex_sdk/methods/fetch_orders.py
xrpl_dex_sdk/methods/fetch_status.py
xrpl_dex_sdk/methods/fetch_ticker.py
xrpl_dex_sdk/methods/fetch_tickers.py
xrpl_dex_sdk/methods/fetch_trades.py
xrpl_dex_sdk/methods/fetch_trading_fee.py
xrpl_dex_sdk/methods/fetch_trading_fees.py
xrpl_dex_sdk/methods/fetch_transaction_fee.py
xrpl_dex_sdk/methods/fetch_transaction_fees.py
xrpl_dex_sdk/methods/fetch_transfer_rate.py
xrpl_dex_sdk/methods/load_currencies.py
xrpl_dex_sdk/methods/load_issuers.py
xrpl_dex_sdk/methods/load_markets.py
xrpl_dex_sdk/methods/watch_balance.py
xrpl_dex_sdk/methods/watch_my_trades.py
xrpl_dex_sdk/methods/watch_order_book.py
xrpl_dex_sdk/methods/watch_orders.py
xrpl_dex_sdk/methods/watch_status.py
xrpl_dex_sdk/methods/watch_ticker.py
xrpl_dex_sdk/methods/watch_tickers.py
xrpl_dex_sdk/methods/watch_trades.py
xrpl_dex_sdk/models/__init__.py
xrpl_dex_sdk/models/base_model.py
xrpl_dex_sdk/models/ccxt/__init__.py
xrpl_dex_sdk/models/ccxt/balances.py
xrpl_dex_sdk-1.0.0.dist-info/LICENSE
xrpl_dex_sdk-1.0.0.dist-info/WHEEL
xrpl_dex_sdk-1.0.0.dist-info/METADATA
xrpl_dex_sdk-1.0.0.dist-info/RECORD
