Metadata-Version: 2.1
Name: xrpl-dex-sdk
Version: 1.0.0
Summary: Python SDK for interacting with the XRPL decentralized exchange
Author: AktaryTech
Author-email: info@aktarytech.com
Requires-Python: >=3.8,<4.0
Classifier: Programming Language :: Python :: 3
Classifier: Programming Language :: Python :: 3.8
Classifier: Programming Language :: Python :: 3.9
Classifier: Programming Language :: Python :: 3.10
Requires-Dist: base58 (>=2.1.1,<3.0.0)
Requires-Dist: pytest (>=7.1.3,<8.0.0)
Requires-Dist: pytest-asyncio (>=0.19.0,<0.20.0)
Requires-Dist: python-dateutil (>=2.8.2,<3.0.0)
Requires-Dist: requests (>=2.28.1,<3.0.0)
Requires-Dist: websockets (>=10.3,<11.0)
Requires-Dist: xrpl-py (>=1.6.0,<2.0.0)
